<?xml version="1.1" encoding="UTF-8" standalone="no"?>
<databaseChangeLog xmlns="http://www.liquibase.org/xml/ns/dbchangelog" xmlns:ext="http://www.liquibase.org/xml/ns/dbchangelog-ext" xmlns:pro="http://www.liquibase.org/xml/ns/pro" xmlns:xsi="http://www.w3.org/2001/XMLSchema-instance" xsi:schemaLocation="http://www.liquibase.org/xml/ns/dbchangelog-ext http://www.liquibase.org/xml/ns/dbchangelog/dbchangelog-ext.xsd http://www.liquibase.org/xml/ns/pro http://www.liquibase.org/xml/ns/pro/liquibase-pro-latest.xsd http://www.liquibase.org/xml/ns/dbchangelog http://www.liquibase.org/xml/ns/dbchangelog/dbchangelog-latest.xsd">
    <changeSet author="Miron (generated)" id="1735911381613-1">
        <createTable tableName="roles">
            <column autoIncrement="true" name="id" startWith="8" type="BIGINT">
                <constraints nullable="false" primaryKey="true" primaryKeyName="roles_pkey"/>
            </column>
            <column name="name" type="VARCHAR(255)"/>
        </createTable>
    </changeSet>
    <changeSet author="Miron (generated)" id="1735911381613-2">
        <createTable tableName="statuses">
            <column autoIncrement="true" name="id" startWith="5" type="BIGINT">
                <constraints nullable="false" primaryKey="true" primaryKeyName="statuses_pkey"/>
            </column>
            <column name="name" type="VARCHAR(255)"/>
        </createTable>
    </changeSet>
    <changeSet author="Miron (generated)" id="1735911381613-3">
        <createTable tableName="tags">
            <column autoIncrement="true" name="id" startWith="12" type="BIGINT">
                <constraints nullable="false" primaryKey="true" primaryKeyName="tags_pkey"/>
            </column>
            <column name="name" type="VARCHAR(255)"/>
        </createTable>
    </changeSet>
    <changeSet author="Miron (generated)" id="1735911381613-4">
        <createTable tableName="tasks">
            <column name="finish_date" type="date"/>
            <column name="start_date" type="date"/>
            <column name="create_by" type="BIGINT"/>
            <column autoIncrement="true" name="id" startWith="8" type="BIGINT">
                <constraints nullable="false" primaryKey="true" primaryKeyName="tasks_pkey"/>
            </column>
            <column name="status_id" type="BIGINT">
                <constraints nullable="false"/>
            </column>
            <column name="body" type="VARCHAR(255)"/>
            <column name="title" type="VARCHAR(255)"/>
        </createTable>
    </changeSet>
    <changeSet author="Miron (generated)" id="1735911381613-5">
        <createTable tableName="users">
            <column autoIncrement="true" name="id" startWith="18" type="BIGINT">
                <constraints nullable="false" primaryKey="true" primaryKeyName="users_pkey"/>
            </column>
            <column name="role_id" type="BIGINT">
                <constraints nullable="false"/>
            </column>
            <column name="email" type="VARCHAR(255)"/>
            <column name="first_name" type="VARCHAR(255)"/>
            <column name="last_name" type="VARCHAR(255)"/>
            <column name="password" type="VARCHAR(255)"/>
        </createTable>
    </changeSet>
    <changeSet author="Miron (generated)" id="1735911381613-6">
        <createTable tableName="tasks_tags">
            <column name="tag_id" type="BIGINT">
                <constraints nullable="false"/>
            </column>
            <column name="task_id" type="BIGINT">
                <constraints nullable="false"/>
            </column>
        </createTable>
    </changeSet>
    <changeSet author="Miron (generated)" id="1735911381613-7">
        <createTable tableName="users_tasks">
            <column name="task_id" type="BIGINT">
                <constraints nullable="false"/>
            </column>
            <column name="user_id" type="BIGINT">
                <constraints nullable="false"/>
            </column>
        </createTable>
    </changeSet>
    <changeSet author="Miron (generated)" id="1735911381613-8">
        <addForeignKeyConstraint baseColumnNames="user_id" baseTableName="users_tasks" constraintName="fk6frwjo48hefay0rg31q970r8t" deferrable="false" initiallyDeferred="false" onDelete="NO ACTION" onUpdate="NO ACTION" referencedColumnNames="id" referencedTableName="users" validate="true"/>
    </changeSet>
    <changeSet author="Miron (generated)" id="1735911381613-9">
        <addForeignKeyConstraint baseColumnNames="task_id" baseTableName="users_tasks" constraintName="fk7todmyl52eiddpi6hc2nfgvbs" deferrable="false" initiallyDeferred="false" onDelete="NO ACTION" onUpdate="NO ACTION" referencedColumnNames="id" referencedTableName="tasks" validate="true"/>
    </changeSet>
    <changeSet author="Miron (generated)" id="1735911381613-10">
        <addForeignKeyConstraint baseColumnNames="tag_id" baseTableName="tasks_tags" constraintName="fk8sfpkkqd4x6n112sxtl4k7yb9" deferrable="false" initiallyDeferred="false" onDelete="NO ACTION" onUpdate="NO ACTION" referencedColumnNames="id" referencedTableName="tags" validate="true"/>
    </changeSet>
    <changeSet author="Miron (generated)" id="1735911381613-11">
        <addForeignKeyConstraint baseColumnNames="task_id" baseTableName="tasks_tags" constraintName="fk92yt3qd8g5o4jm1ck3ca69vbp" deferrable="false" initiallyDeferred="false" onDelete="NO ACTION" onUpdate="NO ACTION" referencedColumnNames="id" referencedTableName="tasks" validate="true"/>
    </changeSet>
    <changeSet author="Miron (generated)" id="1735911381613-12">
        <addForeignKeyConstraint baseColumnNames="status_id" baseTableName="tasks" constraintName="fkhp48vnj340wm1stg2kux5dqcx" deferrable="false" initiallyDeferred="false" onDelete="NO ACTION" onUpdate="NO ACTION" referencedColumnNames="id" referencedTableName="statuses" validate="true"/>
    </changeSet>
    <changeSet author="Miron (generated)" id="1735911381613-13">
        <addForeignKeyConstraint baseColumnNames="role_id" baseTableName="users" constraintName="fkp56c1712k691lhsyewcssf40f" deferrable="false" initiallyDeferred="false" onDelete="NO ACTION" onUpdate="NO ACTION" referencedColumnNames="id" referencedTableName="roles" validate="true"/>
    </changeSet>
</databaseChangeLog>
